src/__init__.py
src/model_pipeline.py
tests/__init__.py
tests/test_dataclass.py
tests/test_pipeline.py
Mlops_ml_deploy_made_iv-0.8.dist-info/METADATA
Mlops_ml_deploy_made_iv-0.8.dist-info/WHEEL
Mlops_ml_deploy_made_iv-0.8.dist-info/top_level.txt
Mlops_ml_deploy_made_iv-0.8.dist-info/RECORD
